branchy/__init__.py
branchy/cli.py
branchy-0.1.0.dist-info/METADATA
branchy-0.1.0.dist-info/WHEEL
branchy-0.1.0.dist-info/entry_points.txt
branchy-0.1.0.dist-info/top_level.txt
branchy-0.1.0.dist-info/RECORD
