Metadata-Version: 2.4
Name: branchy
Version: 0.1.0
Summary: Git branch viewer CLI tool
Home-page: https://taplink.cc/itsqaxxorov
Author: Axmadjon Qaxxorov
License: MIT
Requires-Python: >=3.7
Requires-Dist: rich
Dynamic: home-page
Dynamic: requires-python
